mcp_run/__init__.py
mcp_run/api.py
mcp_run/client.py
mcp_run/config.py
mcp_run/mcp_protocol.py
mcp_run/profile.py
mcp_run/task.py
mcp_run/types.py
mcp_run-0.5.0.dist-info/METADATA
mcp_run-0.5.0.dist-info/WHEEL
mcp_run-0.5.0.dist-info/top_level.txt
mcp_run-0.5.0.dist-info/RECORD
