Metadata-Version: 2.4
Name: mcp-run
Version: 0.5.0
Summary: A Python client for mcp.run
Requires-Python: >=3.10
Requires-Dist: extism>=1.0.4
Requires-Dist: mcp>=1.7.0
Requires-Dist: requests>=2.32.3
